onoffmonitorserver/__init__.py
onoffmonitorserver/admin.py
onoffmonitorserver/apps.py
onoffmonitorserver/filters.py
onoffmonitorserver/models.py
onoffmonitorserver/permissions.py
onoffmonitorserver/serializers.py
onoffmonitorserver/tests.py
onoffmonitorserver/urls.py
onoffmonitorserver/views.py
onoffmonitorserver/migrations/0001_initial.py
onoffmonitorserver/migrations/0002_alter_device_gpio_pin_device_gpio_input_and_more.py
onoffmonitorserver/migrations/0003_monitor_gpio_mode_alter_device_gpio_input.py
onoffmonitorserver/migrations/__init__.py
onoffmonitorserver-0.3.0.dist-info/LICENSE
onoffmonitorserver-0.3.0.dist-info/METADATA
onoffmonitorserver-0.3.0.dist-info/WHEEL
onoffmonitorserver-0.3.0.dist-info/top_level.txt
onoffmonitorserver-0.3.0.dist-info/RECORD
