Metadata-Version: 2.1
Name: onoffmonitorserver
Version: 0.3.0
Summary: Django app for monitoring the on/off status of devices
Author: Joe Greaves
License: The Clear BSD License
Project-URL: Homepage, https://github.com/Grvs44/onoffmonitorserver
Classifier: Programming Language :: Python :: 3
Classifier: License :: OSI Approved :: BSD License
Classifier: Operating System :: OS Independent
Requires-Python: <4,>=3.10
License-File: LICENSE
Requires-Dist: django (>=4.2.3)
Requires-Dist: djangorestframework (>=3.14.0)
Requires-Dist: django-rest-knox (>=4.2.0)
